sqladmin/__init__.py
sqladmin/_menu.py
sqladmin/_queries.py
sqladmin/_types.py
sqladmin/_validators.py
sqladmin/ajax.py
sqladmin/application.py
sqladmin/authentication.py
sqladmin/exceptions.py
sqladmin/fields.py
sqladmin/filters.py
sqladmin/formatters.py
sqladmin/forms.py
sqladmin/helpers.py
sqladmin/models.py
sqladmin/pagination.py
sqladmin/py.typed
sqladmin/templating.py
sqladmin/widgets.py
sqlalchemy_whiteleads-1.4.0.2.dist-info/licenses/LICENSE.md
sqlalchemy_whiteleads-1.4.0.2.dist-info/METADATA
sqlalchemy_whiteleads-1.4.0.2.dist-info/WHEEL
sqlalchemy_whiteleads-1.4.0.2.dist-info/top_level.txt
sqlalchemy_whiteleads-1.4.0.2.dist-info/RECORD
