Metadata-Version: 2.4
Name: sqlalchemy-whiteleads
Version: 1.4.0.2
Summary: Fork of SQLAlchemy with custom modifications
Author-email: Olga Kozynkina <ko3.olga@gmail.com>
License: MIT
Project-URL: Homepage, https://github.com/olga3ok/sqladmin-whiteleads
Classifier: Development Status :: 3 - Alpha
Classifier: Intended Audience :: Developers
Classifier: Programming Language :: Python :: 3
Requires-Python: >=3.7
License-File: LICENSE.md
Dynamic: license-file
Dynamic: requires-python
